weather_retriever/__init__.py
weather_retriever/date.py
weather_retriever/hangul.py
weather_retriever/ner.py
weather_retriever/openai.py
weather_retriever/openweathermap.py
weather_retriever/utils.py
weather_retriever/weather_codes.py
weather_retriever/resources/city_coords.json
weather_retriever-0.1.13.dist-info/LICENSE
weather_retriever-0.1.13.dist-info/METADATA
weather_retriever-0.1.13.dist-info/WHEEL
weather_retriever-0.1.13.dist-info/top_level.txt
weather_retriever-0.1.13.dist-info/RECORD
