Metadata-Version: 2.1
Name: weather-retriever
Version: 0.1.13
Summary: Natural Language Weather Retriever
Home-page: https://github.com/KimRass/weather_retriever
Author: KimRass
Author-email: purflow64@gmail.com
License: Apache License 2.0
Platform: UNKNOWN
License-File: LICENSE
Requires-Dist: torch
Requires-Dist: transformers
Requires-Dist: dateparser
Requires-Dist: requests
Requires-Dist: numpy
